COPYING
ChangeLog
README.html
README.txt
example-firstuse.html
example-firstuse.txt
index-base-uri.txt
indexpackages-man.html
indexpackages-man.txt
indexpackages.py
pkg-info.txt
pypicache.html
pypicache.txt
setup.cfg
setup.py
trailing-slash.txt
./indexpackages.py
pypicache.egg-info/PKG-INFO
pypicache.egg-info/SOURCES.txt
pypicache.egg-info/dependency_links.txt
pypicache.egg-info/entry_points.txt
pypicache.egg-info/top_level.txt
pypicache.egg-info/zip-safe
