Metadata-Version: 1.1
Name: pypicache
Version: 0.2
Summary: The main script provides a relatively painless way to convert a 
Home-page: http://trac.wiretooth.com/public/wiki/pypicache
Author: Robin Bryce
Author-email: ['robinbryce@gmail.com']
License: MIT
Download-URL: http://svn.wiretooth.com/pypi/pypicache/0.2
Platform: UNKNOWN
Classifier: Programming Language :: Python
Provides: p
Provides: y
Provides: p
Provides: i
Provides: c
Provides: a
Provides: c
Provides: h
Provides: e
